moneycontolPy/__init__.py
moneycontolPy/money_control.py
moneycontrolPy/__init__.py
moneycontrolPy/mcp.py
moneycontrolPy/money_control.py
moneycontrolPy/temp.py
moneycontrolPy-0.0.5.dist-info/LICENSE.md
moneycontrolPy-0.0.5.dist-info/METADATA
moneycontrolPy-0.0.5.dist-info/WHEEL
moneycontrolPy-0.0.5.dist-info/top_level.txt
moneycontrolPy-0.0.5.dist-info/RECORD
