Metadata-Version: 2.1
Name: moneycontrolPy
Version: 0.0.5
Summary: A python API for Money Control Forum
Home-page: https://github.com/AkiMosi/moneycontrolPy
Author: Akileshvar A
Author-email: akileshvar008@gmail.com
License: UNKNOWN
Platform: UNKNOWN
Classifier: Programming Language :: Python :: 3
Classifier: License :: OSI Approved :: MIT License
Classifier: Operating System :: OS Independent
Requires-Python: >=3.6
